pylandroidcloud/__init__.py
pylandroidcloud/pylandroidcloud.py
pylandroidcloud-0.2.1.dist-info/AUTHORS.rst
pylandroidcloud-0.2.1.dist-info/LICENSE
pylandroidcloud-0.2.1.dist-info/METADATA
pylandroidcloud-0.2.1.dist-info/WHEEL
pylandroidcloud-0.2.1.dist-info/top_level.txt
pylandroidcloud-0.2.1.dist-info/RECORD
