Metadata-Version: 2.1
Name: pylandroidcloud
Version: 0.2.1
Summary: Small Python package to use the Worx Landroid API
Home-page: https://github.com/colinfrei/pylandroidcloud
Author: Colin Frei
Author-email: git@colinfrei.com
License: MIT license
Keywords: pylandroidcloud
Platform: UNKNOWN
Classifier: Development Status :: 2 - Pre-Alpha
Classifier: Intended Audience :: Developers
Classifier: License :: OSI Approved :: MIT License
Classifier: Natural Language :: English
Classifier: Programming Language :: Python :: 2
Classifier: Programming Language :: Python :: 2.7
Classifier: Programming Language :: Python :: 3
Classifier: Programming Language :: Python :: 3.4
Classifier: Programming Language :: Python :: 3.5
Classifier: Programming Language :: Python :: 3.6
Classifier: Programming Language :: Python :: 3.7
Requires-Dist: paho-mqtt (==1.3.1)
Requires-Dist: pyOpenSSL (==17.5.0)
